pcc-0.2.0.dist-info/DESCRIPTION.rst
pcc-0.2.0.dist-info/METADATA
pcc-0.2.0.dist-info/RECORD
pcc-0.2.0.dist-info/WHEEL
pcc-0.2.0.dist-info/metadata.json
pcc-0.2.0.dist-info/top_level.txt
rtypes/__init__.py
rtypes/connectors/__init__.py
rtypes/connectors/sql.py
rtypes/connectors/xml.py
rtypes/dataframe/__init__.py
rtypes/dataframe/application_queue.py
rtypes/dataframe/change_manager.py
rtypes/dataframe/dataframe.py
rtypes/dataframe/dataframe_client.py
rtypes/dataframe/dataframe_request.py
rtypes/dataframe/dataframe_threading.py
rtypes/dataframe/dataframe_type.py
rtypes/dataframe/object_manager.py
rtypes/dataframe/queue_manager.py
rtypes/dataframe/trigger_manager.py
rtypes/dataframe/type_manager.py
rtypes/dataframe/dataframe_changes/IDataframeChanges.py
rtypes/dataframe/dataframe_changes/__init__.py
rtypes/dataframe/dataframe_changes/dataframe_changes_bson.py
rtypes/dataframe/dataframe_changes/dataframe_changes_cbor.py
rtypes/dataframe/dataframe_changes/dataframe_changes_json.py
rtypes/pcc/__init__.py
rtypes/pcc/attributes.py
rtypes/pcc/create.py
rtypes/pcc/this.py
rtypes/pcc/triggers.py
rtypes/pcc/types/__init__.py
rtypes/pcc/types/impure.py
rtypes/pcc/types/isa.py
rtypes/pcc/types/join.py
rtypes/pcc/types/parameter.py
rtypes/pcc/types/projection.py
rtypes/pcc/types/set.py
rtypes/pcc/types/subset.py
rtypes/pcc/types/union.py
rtypes/pcc/utils/__init__.py
rtypes/pcc/utils/_utils.py
rtypes/pcc/utils/cache.py
rtypes/pcc/utils/enums.py
rtypes/pcc/utils/metadata.py
rtypes/pcc/utils/recursive_dictionary.py
tests/connectors/__init__.py
tests/connectors/test_sql.py
tests/pcc/__init__.py
tests/pcc/test_create.py
tests/pcc/utils/__init__.py
tests/pcc/utils/metadata_tests.py
