Metadata-Version: 2.0
Name: pcc
Version: 0.2.0
Summary: Predicate collection classes
Home-page: https://github.com/Mondego/pcc
Author: Rohan Achar
Author-email: ra.rohan@gmail.com
License: MIT
Keywords: predicate collection classes,design patterns,dataframe,object databases
Platform: UNKNOWN
Classifier: Development Status :: 3 - Alpha
Classifier: Intended Audience :: Developers
Classifier: Intended Audience :: Education
Classifier: Intended Audience :: Science/Research
Classifier: Topic :: Software Development :: Libraries
Classifier: License :: OSI Approved :: MIT License
Classifier: Programming Language :: Python :: 2
Classifier: Programming Language :: Python :: 2.6
Classifier: Programming Language :: Python :: 2.7
Requires-Dist: cbor
Requires-Dist: dill
Provides-Extra: bson
Requires-Dist: bson; extra == 'bson'
Provides-Extra: dev
Provides-Extra: test
